nonebot_plugin_zyk_music/User-Agent.json
nonebot_plugin_zyk_music/__init__.py
nonebot_plugin_zyk_music/config.py
nonebot_plugin_zyk_music/work.py
nonebot_plugin_zyk_music/music/music.txt
nonebot_plugin_zyk_music-0.1.6.2.dist-info/LICENSE
nonebot_plugin_zyk_music-0.1.6.2.dist-info/METADATA
nonebot_plugin_zyk_music-0.1.6.2.dist-info/WHEEL
nonebot_plugin_zyk_music-0.1.6.2.dist-info/top_level.txt
nonebot_plugin_zyk_music-0.1.6.2.dist-info/RECORD
