Metadata-Version: 2.1
Name: nonebot-plugin-zyk-music
Version: 0.1.6.2
Home-page: https://github.com/ZYKsslm/nonebot_plugin_zyk_music
Author: ZSSLM
Author-email: 3119964735@qq.com
License: MIT License
License-File: LICENSE
Requires-Dist: fake-useragent
Requires-Dist: httpx
Requires-Dist: aiohttp
Requires-Dist: colorama
Requires-Dist: filetype
Requires-Dist: nonebot2
Requires-Dist: nonebot-adapter-onebot
